jadio_scraper/__init__.py
jadio_scraper/cli/__init__.py
jadio_scraper/cli/clicommands.json
jadio_scraper/cli/file.py
jadio_scraper/cli/folder.py
jadio_scraper/cli/profile.py
jadio_scraper/cli/url.py
jadio_scraper/core/__init__.py
jadio_scraper/core/compression.py
jadio_scraper/core/csharp.py
jadio_scraper/core/dedup1.py
jadio_scraper/core/dedup2.py
jadio_scraper/core/dedup3.py
jadio_scraper/core/encryption.py
jadio_scraper/core/image.py
jadio_scraper/core/linter.py
jadio_scraper/core/treesitter.py
jadio_scraper/profiles/csharp1.json
jadio_scraper-0.0.1.dist-info/METADATA
jadio_scraper-0.0.1.dist-info/WHEEL
jadio_scraper-0.0.1.dist-info/licenses/LICENSE
jadio_scraper-0.0.1.dist-info/RECORD
